{
  "rooms": [
    {
      "id": "639bc4d83b867100010cf851",
      "ownerID": "639af2c9c6355b1cd52fe516",
      "owner": {
        "userID": "639af2c9c6355b1cd52fe516",
        "displayName": "Apolostudios"
      },
      "name": "Plaza Mayor Valladolid (Spain)",
      "slug": "Plaza-Mayor-Valladolid-Spain",
      "description": ".",
      "tags": [
        "party",
        "turism",
        "spain",
        "valladolid",
        "trendy"
      ],
      "orgOwner": {
        "id": "",
        "name": "",
        "subscription": {
          "subscriptionType": "",
          "subscriptionSource": "",
          "isActive": false
        }
      },
      "organizations": null,
      "timeLastJoined": "0001-01-01T00:00:00Z",
      "thumbnails": [],
      "activeParticipants": [
        {
          "id": "63834d87c3c40face2aed2d5",
          "displayName": "Julio33",
          "profilePicURL": "https://renderapi.s3.amazonaws.com/CniAvudnU.png",
          "avatarData": {
            "avatarUserID": "cf835f0c-2543-45ac-98a1-e0f441eefaf8",
            "avatarID": "fb35900e-758c-438a-97b9-cb8de7c16cab",
            "avatarBody": "https://dd2cgqlmnwvp5.cloudfront.net/avatar_generic_bodies/rpm_male_formal/model.glb",
            "filename": "",
            "skinColorOverride": "",
            "shirtColorOverride": "",
            "readyPlayerMeID": "",
            "readyPlayerMeAvatarID": "",
            "readyPlayerMeThumbnails": {
              "upperBody": "https://renderapi.s3.amazonaws.com/CniAvudnU.png",
              "lowerBody": ""
            },
            "readyPlayerMeUrl": "https://models.readyplayer.me/6383506ba7399ec52239de77.glb",
            "ReadyPlayerMeUrlLastUpdated": "0001-01-01T00:00:00Z",
            "readyPlayerMeUrlCrunched": "",
            "readyPlayerMeUrlCrunchedBrotli": "",
            "ReadyPlayerMeUrlCrunchedLastUpdated": "0001-01-01T00:00:00Z",
            "activeAvatarStyle": "READY_PLAYER_ME"
          },
          "appearanceCustomization": {
            "profileColor": "pink"
          },
          "clientPlatforms": [
            "Web"
          ],
          "permissions": []
        },
        {
          "id": "64f21bad14b03f63dc457593",
          "displayName": "Lurbego",
          "profilePicURL": "",
          "avatarData": {
            "avatarUserID": "",
            "avatarID": "",
            "avatarBody": "",
            "filename": "",
            "skinColorOverride": "",
            "shirtColorOverride": "",
            "readyPlayerMeID": "",
            "readyPlayerMeAvatarID": "",
            "readyPlayerMeThumbnails": {
              "upperBody": "",
              "lowerBody": ""
            },
            "readyPlayerMeUrl": "",
            "ReadyPlayerMeUrlLastUpdated": "0001-01-01T00:00:00Z",
            "readyPlayerMeUrlCrunched": "",
            "readyPlayerMeUrlCrunchedBrotli": "",
            "ReadyPlayerMeUrlCrunchedLastUpdated": "0001-01-01T00:00:00Z",
            "activeAvatarStyle": "REALISTIC"
          },
          "appearanceCustomization": {
            "profileColor": "blue"
          },
          "clientPlatforms": [
            "Web"
          ],
          "permissions": []
        },
        {
          "id": "639af2c9c6355b1cd52fe516",
          "displayName": "Apolostudios",
          "profilePicURL": "https://renderapi.s3.amazonaws.com/Cb4pxJNou.png",
          "avatarData": {
            "avatarUserID": "",
            "avatarID": "",
            "avatarBody": "https://dd2cgqlmnwvp5.cloudfront.net/avatar_generic_bodies/rpm_female_jacket/model.glb",
            "filename": "",
            "skinColorOverride": "",
            "shirtColorOverride": "",
            "readyPlayerMeID": "",
            "readyPlayerMeAvatarID": "",
            "readyPlayerMeThumbnails": {
              "upperBody": "https://renderapi.s3.amazonaws.com/Cb4pxJNou.png",
              "lowerBody": ""
            },
            "readyPlayerMeUrl": "https://models.readyplayer.me/639af4d00eab23107f35642d.glb?updatedAt=1686746863084",
            "ReadyPlayerMeUrlLastUpdated": "0001-01-01T00:00:00Z",
            "readyPlayerMeUrlCrunched": "",
            "readyPlayerMeUrlCrunchedBrotli": "",
            "ReadyPlayerMeUrlCrunchedLastUpdated": "0001-01-01T00:00:00Z",
            "activeAvatarStyle": "READY_PLAYER_ME"
          },
          "appearanceCustomization": {
            "profileColor": "tan"
          },
          "clientPlatforms": [
            "Web",
            "Web",
            "Web",
            "Web"
          ],
          "permissions": []
        },
        {
          "id": "64f1b1e258e94e07225d2e3a",
          "displayName": "Kingkonye",
          "profilePicURL": "https://dd2cgqlmnwvp5.cloudfront.net/avatar_generic_bodies/rpm_male_baggy_jacket/thumbnail.png",
          "avatarData": {
            "avatarUserID": "",
            "avatarID": "",
            "avatarBody": "https://dd2cgqlmnwvp5.cloudfront.net/avatar_generic_bodies/rpm_male_baggy_jacket/model.glb",
            "filename": "",
            "skinColorOverride": "f3eddb",
            "shirtColorOverride": "ff5f42",
            "readyPlayerMeID": "",
            "readyPlayerMeAvatarID": "",
            "readyPlayerMeThumbnails": {
              "upperBody": "",
              "lowerBody": ""
            },
            "readyPlayerMeUrl": "",
            "ReadyPlayerMeUrlLastUpdated": "0001-01-01T00:00:00Z",
            "readyPlayerMeUrlCrunched": "",
            "readyPlayerMeUrlCrunchedBrotli": "",
            "ReadyPlayerMeUrlCrunchedLastUpdated": "0001-01-01T00:00:00Z",
            "activeAvatarStyle": "REALISTIC"
          },
          "appearanceCustomization": {
            "profileColor": "purple"
          },
          "clientPlatforms": [
            "Web"
          ],
          "permissions": []
        }
      ],
      "polymerVersion": 19,
      "roomThumbnails": {
        "customGetUrl": "https://cdn.spatial.io/assets/v1/thumbnails/639bc4d83b867100010cf851/customThumbnail/r/1c858d6e18ed849fde0d6677ed6bdf4f8d6d6cac84a832eff5b093a91b0814b1/1693589693",
        "transientGetUrl": "https://cdn.spatial.io/assets/v1/thumbnails/639bc4d83b867100010cf851/transientStateThumbnail/r/949f178d1b98c39315bda85aaf914e6fc78d9a310cbc133f9fd9f0c42133b039/1693589693",
        "persistentGetUrl": "https://cdn.spatial.io/assets/v1/thumbnails/639bc4d83b867100010cf851/persistentStateThumbnail/r/ab18538732bf22d13b0baf483a23b113a6850b2507cef06ab0664087ebb14b59/1693589693",
        "cubemapGetUrl": "https://cdn.spatial.io/assets/v1/thumbnails/639bc4d83b867100010cf851/cubemap/r/03070ba11588e8141004cf6f5ed6080f1dd536e9e4045bbcfe311bf6419a44d9/1693589693",
        "expiresAt": 1693604114
      },
      "thumbnail": "https://cdn.spatial.io/assets/v1/thumbnails/639bc4d83b867100010cf851/customThumbnail/r/1c858d6e18ed849fde0d6677ed6bdf4f8d6d6cac84a832eff5b093a91b0814b1/1693589693",
      "cubeMap": "https://cdn.spatial.io/assets/v1/thumbnails/639bc4d83b867100010cf851/cubemap/r/03070ba11588e8141004cf6f5ed6080f1dd536e9e4045bbcfe311bf6419a44d9/1693589693",
      "starred": true,
      "sandbox": false,
      "shareID": "6871682445212284257",
      "code": "",
      "shareSetting": "ORG",
      "publicLink": true,
      "roomAdmins": [
        "62cfe0d21111938e99737620",
        "62cffe2bb921b8527a6a4007"
      ],
      "restrictedPermissions": [
        "RESTRICT_OTHERS_VIEW_ONLY"
      ],
      "directlyInvitedGuests": {},
      "lobbyType": "",
      "published": true,
      "defaultRoomContent": null,
      "accessible": true,
      "createdAt": "2022-12-16T01:07:36.975Z",
      "tileSize": "large",
      "isNFTSpace": false,
      "isCreatorToolkitSpace": false,
      "packageSKU": "",
      "worldID": "",
      "directlyInvitedGuestsArray": [],
      "active": true,
      "users": [
        "63834d87c3c40face2aed2d5",
        "64f21bad14b03f63dc457593",
        "639af2c9c6355b1cd52fe516",
        "64f1b1e258e94e07225d2e3a"
      ],
      "activeParticipantCount": 7,
      "likes": 205,
      "views": 3620,
      "isInstanceable": false,
      "likedSpace": false,
      "promoted": true,
      "lastPromoted": "2023-09-01T17:31:19.623727Z"
    }
  ],
  "paging": {
    "total": 1
  }
}
