{
  "rooms": [
    {
      "id": "639bc4d83b867100010cf851",
      "ownerID": "639af2c9c6355b1cd52fe516",
      "owner": {
        "userID": "639af2c9c6355b1cd52fe516",
        "displayName": "Apolostudios / Metaverse Developer"
      },
      "name": "Plaza Mayor Valladolid (Spain)-  Ferias y Fiestas Virgen San Lorenzo 2023",
      "slug": "Plaza-Mayor-Valladolid-Spain-Ferias-y-Fiestas-Virgen-San-Lorenzo-2023",
      "description": "Vive en directo el pregón, el record guiness y el espectaculo piromusical de las ferias y fiestas de Valladolid.",
      "tags": [
        "valladolid",
        "trendy",
        "party",
        "turism",
        "spain"
      ],
      "orgOwner": {
        "id": "",
        "name": "",
        "subscription": {
          "subscriptionType": "",
          "subscriptionSource": "",
          "isActive": false
        }
      },
      "organizations": null,
      "timeLastJoined": "0001-01-01T00:00:00Z",
      "thumbnails": [],
      "activeParticipants": [
        {
          "id": "639af2c9c6355b1cd52fe516",
          "displayName": "Apolostudios / Metaverse Developer",
          "profilePicURL": "https://renderapi.s3.amazonaws.com/Cb4pxJNou.png",
          "avatarData": {
            "avatarUserID": "",
            "avatarID": "",
            "avatarBody": "spatialcontent://item:s6psffI4GQJl-bfLtJawO",
            "filename": "",
            "skinColorOverride": "",
            "shirtColorOverride": "",
            "readyPlayerMeID": "",
            "readyPlayerMeAvatarID": "",
            "readyPlayerMeThumbnails": {
              "upperBody": "https://renderapi.s3.amazonaws.com/Cb4pxJNou.png",
              "lowerBody": ""
            },
            "readyPlayerMeUrl": "https://models.readyplayer.me/639af4d00eab23107f35642d.glb?updatedAt=1686746863084",
            "ReadyPlayerMeUrlLastUpdated": "0001-01-01T00:00:00Z",
            "readyPlayerMeUrlCrunched": "",
            "readyPlayerMeUrlCrunchedBrotli": "",
            "ReadyPlayerMeUrlCrunchedLastUpdated": "0001-01-01T00:00:00Z",
            "activeAvatarStyle": "CREATOR_TOOLKIT"
          },
          "appearanceCustomization": {
            "profileColor": "tan"
          },
          "clientPlatforms": [
            "Web",
            "Web",
            "Web",
            "Web",
            "Web",
            "Web",
            "Web",
            "Web",
            "Web"
          ],
          "permissions": []
        }
      ],
      "polymerVersion": 19,
      "roomThumbnails": {
        "customGetUrl": "https://cdn.spatial.io/assets/v1/thumbnails/639bc4d83b867100010cf851/customThumbnail/r/f37d6b5476e410e205e7a14dfdeb260c53e2ba2876c1932852749f2f907a3548/1694167086",
        "transientGetUrl": "https://cdn.spatial.io/assets/v1/thumbnails/639bc4d83b867100010cf851/transientStateThumbnail/r/0706b53f579e1a581eff4236096e60122f909cac71dddf2f0698e98138fbca86/1694167086",
        "persistentGetUrl": "https://cdn.spatial.io/assets/v1/thumbnails/639bc4d83b867100010cf851/persistentStateThumbnail/r/4dd45e733eed1a581dceb17876884cd8c8bd48356b312a782cea7e9a41664572/1694167086",
        "cubemapGetUrl": "https://cdn.spatial.io/assets/v1/thumbnails/639bc4d83b867100010cf851/cubemap/r/fc716476f674a249ec9c80c8bf9d91a786218f48afef92caa6d56c37ea489831/1694167086",
        "expiresAt": 1694181548
      },
      "thumbnail": "https://cdn.spatial.io/assets/v1/thumbnails/639bc4d83b867100010cf851/customThumbnail/r/f37d6b5476e410e205e7a14dfdeb260c53e2ba2876c1932852749f2f907a3548/1694167086",
      "cubeMap": "https://cdn.spatial.io/assets/v1/thumbnails/639bc4d83b867100010cf851/cubemap/r/fc716476f674a249ec9c80c8bf9d91a786218f48afef92caa6d56c37ea489831/1694167086",
      "starred": true,
      "sandbox": false,
      "shareID": "6871682445212284257",
      "code": "",
      "shareSetting": "ORG",
      "publicLink": true,
      "roomAdmins": [
        "62cfe0d21111938e99737620",
        "62cffe2bb921b8527a6a4007"
      ],
      "restrictedPermissions": [
        "RESTRICT_OTHERS_VIEW_ONLY"
      ],
      "directlyInvitedGuests": {},
      "lobbyType": "",
      "published": true,
      "defaultRoomContent": null,
      "accessible": true,
      "createdAt": "2022-12-16T01:07:36.975Z",
      "isNFTSpace": false,
      "isCreatorToolkitSpace": false,
      "packageSKU": "",
      "worldID": "",
      "directlyInvitedGuestsArray": [],
      "active": true,
      "users": [
        "639af2c9c6355b1cd52fe516"
      ],
      "activeParticipantCount": 9,
      "likes": 249,
      "views": 4578,
      "isInstanceable": false,
      "likedSpace": false,
      "promoted": true,
      "lastPromoted": "2023-09-06T14:40:14.017529Z"
    }
  ],
  "paging": {
    "total": 1
  }
}
